{
  "columns": [
    {
      "id": "us/census/acs/B17010D001_moe"
    }, 
    {
      "id": "us/census/acs/B17010D002_moe"
    }, 
    {
      "id": "us/census/acs/B17010D003_moe"
    }, 
    {
      "id": "us/census/acs/B17010D004_moe"
    }, 
    {
      "id": "us/census/acs/B17010D005_moe"
    }, 
    {
      "id": "us/census/acs/B17010D006_moe"
    }, 
    {
      "id": "us/census/acs/B17010D007_moe"
    }, 
    {
      "id": "us/census/acs/B17010D008_moe"
    }, 
    {
      "id": "us/census/acs/B17010D009_moe"
    }, 
    {
      "id": "us/census/acs/B17010D010_moe"
    }, 
    {
      "id": "us/census/acs/B17010D011_moe"
    }, 
    {
      "id": "us/census/acs/B17010D012_moe"
    }, 
    {
      "id": "us/census/acs/B17010D013_moe"
    }, 
    {
      "id": "us/census/acs/B17010D014_moe"
    }, 
    {
      "id": "us/census/acs/B17010D015_moe"
    }, 
    {
      "id": "us/census/acs/B17010D016_moe"
    }, 
    {
      "id": "us/census/acs/B17010D017_moe"
    }, 
    {
      "id": "us/census/acs/B17010D018_moe"
    }, 
    {
      "id": "us/census/acs/B17010D019_moe"
    }, 
    {
      "id": "us/census/acs/B17010D020_moe"
    }, 
    {
      "id": "us/census/acs/B17010D021_moe"
    }, 
    {
      "id": "us/census/acs/B17010D022_moe"
    }, 
    {
      "id": "us/census/acs/B17010D023_moe"
    }, 
    {
      "id": "us/census/acs/B17010D024_moe"
    }, 
    {
      "id": "us/census/acs/B17010D025_moe"
    }, 
    {
      "id": "us/census/acs/B17010D026_moe"
    }, 
    {
      "id": "us/census/acs/B17010D027_moe"
    }, 
    {
      "id": "us/census/acs/B17010D028_moe"
    }, 
    {
      "id": "us/census/acs/B17010D029_moe"
    }, 
    {
      "id": "us/census/acs/B17010D030_moe"
    }, 
    {
      "id": "us/census/acs/B17010D031_moe"
    }, 
    {
      "id": "us/census/acs/B17010D032_moe"
    }, 
    {
      "id": "us/census/acs/B17010D033_moe"
    }, 
    {
      "id": "us/census/acs/B17010D034_moe"
    }, 
    {
      "id": "us/census/acs/B17010D035_moe"
    }, 
    {
      "id": "us/census/acs/B17010D036_moe"
    }, 
    {
      "id": "us/census/acs/B17010D037_moe"
    }, 
    {
      "id": "us/census/acs/B17010D038_moe"
    }, 
    {
      "id": "us/census/acs/B17010D039_moe"
    }, 
    {
      "id": "us/census/acs/B17010D040_moe"
    }, 
    {
      "id": "us/census/acs/B17010D041_moe"
    }, 
    {
      "id": "us/census/acs/B17010E001_moe"
    }, 
    {
      "id": "us/census/acs/B17010E002_moe"
    }, 
    {
      "id": "us/census/acs/B17010E003_moe"
    }, 
    {
      "id": "us/census/acs/B17010E004_moe"
    }, 
    {
      "id": "us/census/acs/B17010E005_moe"
    }, 
    {
      "id": "us/census/acs/B17010E006_moe"
    }, 
    {
      "id": "us/census/acs/B17010E007_moe"
    }, 
    {
      "id": "us/census/acs/B17010E008_moe"
    }, 
    {
      "id": "us/census/acs/B17010E009_moe"
    }, 
    {
      "id": "us/census/acs/B17010E010_moe"
    }, 
    {
      "id": "us/census/acs/B17010E011_moe"
    }, 
    {
      "id": "us/census/acs/B17010E012_moe"
    }, 
    {
      "id": "us/census/acs/B17010E013_moe"
    }, 
    {
      "id": "us/census/acs/B17010E014_moe"
    }, 
    {
      "id": "us/census/acs/B17010E015_moe"
    }, 
    {
      "id": "us/census/acs/B17010E016_moe"
    }, 
    {
      "id": "us/census/acs/B17010E017_moe"
    }, 
    {
      "id": "us/census/acs/B17010E018_moe"
    }, 
    {
      "id": "us/census/acs/B17010E019_moe"
    }, 
    {
      "id": "us/census/acs/B17010E020_moe"
    }, 
    {
      "id": "us/census/acs/B17010E021_moe"
    }, 
    {
      "id": "us/census/acs/B17010E022_moe"
    }, 
    {
      "id": "us/census/acs/B17010E023_moe"
    }, 
    {
      "id": "us/census/acs/B17010E024_moe"
    }, 
    {
      "id": "us/census/acs/B17010E025_moe"
    }, 
    {
      "id": "us/census/acs/B17010E026_moe"
    }, 
    {
      "id": "us/census/acs/B17010E027_moe"
    }, 
    {
      "id": "us/census/acs/B17010E028_moe"
    }, 
    {
      "id": "us/census/acs/B17010E029_moe"
    }, 
    {
      "id": "us/census/acs/B17010E030_moe"
    }, 
    {
      "id": "us/census/acs/B17010E031_moe"
    }, 
    {
      "id": "us/census/acs/B17010E032_moe"
    }, 
    {
      "id": "us/census/acs/B17010E033_moe"
    }, 
    {
      "id": "us/census/acs/B17010E034_moe"
    }, 
    {
      "id": "us/census/acs/B17010E035_moe"
    }, 
    {
      "id": "us/census/acs/B17010E036_moe"
    }, 
    {
      "id": "us/census/acs/B17010E037_moe"
    }, 
    {
      "id": "us/census/acs/B17010E038_moe"
    }, 
    {
      "id": "us/census/acs/B17010E039_moe"
    }, 
    {
      "id": "us/census/acs/B17010E040_moe"
    }, 
    {
      "id": "us/census/acs/B17010E041_moe"
    }, 
    {
      "id": "us/census/acs/B17010F001_moe"
    }, 
    {
      "id": "us/census/acs/B17010F002_moe"
    }, 
    {
      "id": "us/census/acs/B17010F003_moe"
    }, 
    {
      "id": "us/census/acs/B17010F004_moe"
    }, 
    {
      "id": "us/census/acs/B17010F005_moe"
    }, 
    {
      "id": "us/census/acs/B17010F006_moe"
    }, 
    {
      "id": "us/census/acs/B17010F007_moe"
    }, 
    {
      "id": "us/census/acs/B17010F008_moe"
    }, 
    {
      "id": "us/census/acs/B17010F009_moe"
    }, 
    {
      "id": "us/census/acs/B17010F010_moe"
    }, 
    {
      "id": "us/census/acs/B17010F011_moe"
    }, 
    {
      "id": "us/census/acs/B17010F012_moe"
    }, 
    {
      "id": "us/census/acs/B17010F013_moe"
    }, 
    {
      "id": "us/census/acs/B17010F014_moe"
    }, 
    {
      "id": "us/census/acs/B17010F015_moe"
    }, 
    {
      "id": "us/census/acs/B17010F016_moe"
    }, 
    {
      "id": "us/census/acs/B17010F017_moe"
    }, 
    {
      "id": "us/census/acs/B17010F018_moe"
    }, 
    {
      "id": "us/census/acs/B17010F019_moe"
    }, 
    {
      "id": "us/census/acs/B17010F020_moe"
    }, 
    {
      "id": "us/census/acs/B17010F021_moe"
    }, 
    {
      "id": "us/census/acs/B17010F022_moe"
    }, 
    {
      "id": "us/census/acs/B17010F023_moe"
    }, 
    {
      "id": "us/census/acs/B17010F024_moe"
    }, 
    {
      "id": "us/census/acs/B17010F025_moe"
    }, 
    {
      "id": "us/census/acs/B17010F026_moe"
    }, 
    {
      "id": "us/census/acs/B17010F027_moe"
    }, 
    {
      "id": "us/census/acs/B17010F028_moe"
    }, 
    {
      "id": "us/census/acs/B17010F029_moe"
    }, 
    {
      "id": "us/census/acs/B17010F030_moe"
    }, 
    {
      "id": "us/census/acs/B17010F031_moe"
    }, 
    {
      "id": "us/census/acs/B17010F032_moe"
    }, 
    {
      "id": "us/census/acs/B17010F033_moe"
    }, 
    {
      "id": "us/census/acs/B17010F034_moe"
    }, 
    {
      "id": "us/census/acs/B17010F035_moe"
    }, 
    {
      "id": "us/census/acs/B17010F036_moe"
    }, 
    {
      "id": "us/census/acs/B17010F037_moe"
    }, 
    {
      "id": "us/census/acs/B17010F038_moe"
    }, 
    {
      "id": "us/census/acs/B17010F039_moe"
    }, 
    {
      "id": "us/census/acs/B17010F040_moe"
    }, 
    {
      "id": "us/census/acs/B17010F041_moe"
    }, 
    {
      "id": "us/census/acs/B17010G001_moe"
    }, 
    {
      "id": "us/census/acs/B17010G002_moe"
    }, 
    {
      "id": "us/census/acs/B17010G003_moe"
    }, 
    {
      "id": "us/census/acs/B17010G004_moe"
    }, 
    {
      "id": "us/census/acs/B17010G005_moe"
    }, 
    {
      "id": "us/census/acs/B17010G006_moe"
    }, 
    {
      "id": "us/census/acs/B17010G007_moe"
    }, 
    {
      "id": "us/census/acs/B17010G008_moe"
    }, 
    {
      "id": "us/census/acs/B17010G009_moe"
    }, 
    {
      "id": "us/census/acs/B17010G010_moe"
    }, 
    {
      "id": "us/census/acs/B17010G011_moe"
    }, 
    {
      "id": "us/census/acs/B17010G012_moe"
    }, 
    {
      "id": "us/census/acs/B17010G013_moe"
    }, 
    {
      "id": "us/census/acs/B17010G014_moe"
    }, 
    {
      "id": "us/census/acs/B17010G015_moe"
    }, 
    {
      "id": "us/census/acs/B17010G016_moe"
    }, 
    {
      "id": "us/census/acs/B17010G017_moe"
    }, 
    {
      "id": "us/census/acs/B17010G018_moe"
    }, 
    {
      "id": "us/census/acs/B17010G019_moe"
    }, 
    {
      "id": "us/census/acs/B17010G020_moe"
    }, 
    {
      "id": "us/census/acs/B17010G021_moe"
    }, 
    {
      "id": "us/census/acs/B17010G022_moe"
    }, 
    {
      "id": "us/census/acs/B17010G023_moe"
    }, 
    {
      "id": "us/census/acs/B17010G024_moe"
    }, 
    {
      "id": "us/census/acs/B17010G025_moe"
    }, 
    {
      "id": "us/census/acs/B17010G026_moe"
    }, 
    {
      "id": "us/census/acs/B17010G027_moe"
    }, 
    {
      "id": "us/census/acs/B17010G028_moe"
    }, 
    {
      "id": "us/census/acs/B17010G029_moe"
    }, 
    {
      "id": "us/census/acs/B17010G030_moe"
    }, 
    {
      "id": "us/census/acs/B17010G031_moe"
    }, 
    {
      "id": "us/census/acs/B17010G032_moe"
    }, 
    {
      "id": "us/census/acs/B17010G033_moe"
    }, 
    {
      "id": "us/census/acs/B17010G034_moe"
    }, 
    {
      "id": "us/census/acs/B17010G035_moe"
    }, 
    {
      "id": "us/census/acs/B17010G036_moe"
    }, 
    {
      "id": "us/census/acs/B17010G037_moe"
    }, 
    {
      "id": "us/census/acs/B17010G038_moe"
    }, 
    {
      "id": "us/census/acs/B17010G039_moe"
    }, 
    {
      "id": "us/census/acs/B17010G040_moe"
    }, 
    {
      "id": "us/census/acs/B17010G041_moe"
    }, 
    {
      "id": "us/census/acs/B17010H001_moe"
    }, 
    {
      "id": "us/census/acs/B17010H002_moe"
    }, 
    {
      "id": "us/census/acs/B17010H003_moe"
    }, 
    {
      "id": "us/census/acs/B17010H004_moe"
    }, 
    {
      "id": "us/census/acs/B17010H005_moe"
    }, 
    {
      "id": "us/census/acs/B17010H006_moe"
    }, 
    {
      "id": "us/census/acs/B17010H007_moe"
    }, 
    {
      "id": "us/census/acs/B17010H008_moe"
    }, 
    {
      "id": "us/census/acs/B17010H009_moe"
    }, 
    {
      "id": "us/census/acs/B17010H010_moe"
    }, 
    {
      "id": "us/census/acs/B17010H011_moe"
    }, 
    {
      "id": "us/census/acs/B17010H012_moe"
    }, 
    {
      "id": "us/census/acs/B17010H013_moe"
    }, 
    {
      "id": "us/census/acs/B17010H014_moe"
    }, 
    {
      "id": "us/census/acs/B17010H015_moe"
    }, 
    {
      "id": "us/census/acs/B17010H016_moe"
    }, 
    {
      "id": "us/census/acs/B17010H017_moe"
    }, 
    {
      "id": "us/census/acs/B17010H018_moe"
    }, 
    {
      "id": "us/census/acs/B17010H019_moe"
    }, 
    {
      "id": "us/census/acs/B17010H020_moe"
    }, 
    {
      "id": "us/census/acs/B17010H021_moe"
    }, 
    {
      "id": "us/census/acs/B17010H022_moe"
    }, 
    {
      "id": "us/census/acs/B17010H023_moe"
    }, 
    {
      "id": "us/census/acs/B17010H024_moe"
    }, 
    {
      "id": "us/census/acs/B17010H025_moe"
    }, 
    {
      "id": "us/census/acs/B17010H026_moe"
    }, 
    {
      "id": "us/census/acs/B17010H027_moe"
    }, 
    {
      "id": "us/census/acs/B17010H028_moe"
    }, 
    {
      "id": "us/census/acs/B17010H029_moe"
    }, 
    {
      "id": "us/census/acs/B17010H030_moe"
    }, 
    {
      "id": "us/census/acs/B17010H031_moe"
    }, 
    {
      "id": "us/census/acs/B17010H032_moe"
    }, 
    {
      "id": "us/census/acs/B17010H033_moe"
    }, 
    {
      "id": "us/census/acs/B17010H034_moe"
    }, 
    {
      "id": "us/census/acs/B17010H035_moe"
    }, 
    {
      "id": "us/census/acs/B17010H036_moe"
    }, 
    {
      "id": "us/census/acs/B17010H037_moe"
    }, 
    {
      "id": "us/census/acs/B17010H038_moe"
    }, 
    {
      "id": "us/census/acs/B17010H039_moe"
    }, 
    {
      "id": "us/census/acs/B17010H040_moe"
    }, 
    {
      "id": "us/census/acs/B17010H041_moe"
    }
  ], 
  "dct_temporal_sm": "2008 - 2012", 
  "title": "acs2012_5yr seq0051_moe"
}