{
  "columns": [
    {
      "id": "us/census/acs/B04001001_moe"
    }, 
    {
      "id": "us/census/acs/B04001002_moe"
    }, 
    {
      "id": "us/census/acs/B04001003_moe"
    }, 
    {
      "id": "us/census/acs/B04001004_moe"
    }, 
    {
      "id": "us/census/acs/B04001005_moe"
    }, 
    {
      "id": "us/census/acs/B04001006_moe"
    }, 
    {
      "id": "us/census/acs/B04001007_moe"
    }, 
    {
      "id": "us/census/acs/B04001008_moe"
    }, 
    {
      "id": "us/census/acs/B04001009_moe"
    }, 
    {
      "id": "us/census/acs/B04001010_moe"
    }, 
    {
      "id": "us/census/acs/B04001011_moe"
    }, 
    {
      "id": "us/census/acs/B04001012_moe"
    }, 
    {
      "id": "us/census/acs/B04001013_moe"
    }, 
    {
      "id": "us/census/acs/B04001014_moe"
    }, 
    {
      "id": "us/census/acs/B04001015_moe"
    }, 
    {
      "id": "us/census/acs/B04001016_moe"
    }, 
    {
      "id": "us/census/acs/B04001017_moe"
    }, 
    {
      "id": "us/census/acs/B04001018_moe"
    }, 
    {
      "id": "us/census/acs/B04001019_moe"
    }, 
    {
      "id": "us/census/acs/B04001020_moe"
    }, 
    {
      "id": "us/census/acs/B04001021_moe"
    }, 
    {
      "id": "us/census/acs/B04001022_moe"
    }, 
    {
      "id": "us/census/acs/B04001023_moe"
    }, 
    {
      "id": "us/census/acs/B04001024_moe"
    }, 
    {
      "id": "us/census/acs/B04001025_moe"
    }, 
    {
      "id": "us/census/acs/B04001026_moe"
    }, 
    {
      "id": "us/census/acs/B04001027_moe"
    }, 
    {
      "id": "us/census/acs/B04001028_moe"
    }, 
    {
      "id": "us/census/acs/B04001029_moe"
    }, 
    {
      "id": "us/census/acs/B04001030_moe"
    }, 
    {
      "id": "us/census/acs/B04001031_moe"
    }, 
    {
      "id": "us/census/acs/B04001032_moe"
    }, 
    {
      "id": "us/census/acs/B04001033_moe"
    }, 
    {
      "id": "us/census/acs/B04001034_moe"
    }, 
    {
      "id": "us/census/acs/B04001035_moe"
    }, 
    {
      "id": "us/census/acs/B04001036_moe"
    }, 
    {
      "id": "us/census/acs/B04001037_moe"
    }, 
    {
      "id": "us/census/acs/B04001038_moe"
    }, 
    {
      "id": "us/census/acs/B04001039_moe"
    }, 
    {
      "id": "us/census/acs/B04001040_moe"
    }, 
    {
      "id": "us/census/acs/B04001041_moe"
    }, 
    {
      "id": "us/census/acs/B04001042_moe"
    }, 
    {
      "id": "us/census/acs/B04001043_moe"
    }, 
    {
      "id": "us/census/acs/B04001044_moe"
    }, 
    {
      "id": "us/census/acs/B04001045_moe"
    }, 
    {
      "id": "us/census/acs/B04001046_moe"
    }, 
    {
      "id": "us/census/acs/B04001047_moe"
    }, 
    {
      "id": "us/census/acs/B04001048_moe"
    }, 
    {
      "id": "us/census/acs/B04001049_moe"
    }, 
    {
      "id": "us/census/acs/B04001050_moe"
    }, 
    {
      "id": "us/census/acs/B04001051_moe"
    }, 
    {
      "id": "us/census/acs/B04001052_moe"
    }, 
    {
      "id": "us/census/acs/B04001053_moe"
    }, 
    {
      "id": "us/census/acs/B04001054_moe"
    }, 
    {
      "id": "us/census/acs/B04001055_moe"
    }, 
    {
      "id": "us/census/acs/B04001056_moe"
    }, 
    {
      "id": "us/census/acs/B04001057_moe"
    }, 
    {
      "id": "us/census/acs/B04001058_moe"
    }, 
    {
      "id": "us/census/acs/B04001059_moe"
    }, 
    {
      "id": "us/census/acs/B04001060_moe"
    }, 
    {
      "id": "us/census/acs/B04001061_moe"
    }, 
    {
      "id": "us/census/acs/B04001062_moe"
    }, 
    {
      "id": "us/census/acs/B04001063_moe"
    }, 
    {
      "id": "us/census/acs/B04001064_moe"
    }, 
    {
      "id": "us/census/acs/B04001065_moe"
    }, 
    {
      "id": "us/census/acs/B04001066_moe"
    }, 
    {
      "id": "us/census/acs/B04001067_moe"
    }, 
    {
      "id": "us/census/acs/B04001068_moe"
    }, 
    {
      "id": "us/census/acs/B04001069_moe"
    }, 
    {
      "id": "us/census/acs/B04001070_moe"
    }, 
    {
      "id": "us/census/acs/B04001071_moe"
    }, 
    {
      "id": "us/census/acs/B04001072_moe"
    }, 
    {
      "id": "us/census/acs/B04001073_moe"
    }, 
    {
      "id": "us/census/acs/B04001074_moe"
    }, 
    {
      "id": "us/census/acs/B04001075_moe"
    }, 
    {
      "id": "us/census/acs/B04001076_moe"
    }, 
    {
      "id": "us/census/acs/B04001077_moe"
    }, 
    {
      "id": "us/census/acs/B04001078_moe"
    }, 
    {
      "id": "us/census/acs/B04001079_moe"
    }, 
    {
      "id": "us/census/acs/B04001080_moe"
    }, 
    {
      "id": "us/census/acs/B04001081_moe"
    }, 
    {
      "id": "us/census/acs/B04001082_moe"
    }, 
    {
      "id": "us/census/acs/B04001083_moe"
    }, 
    {
      "id": "us/census/acs/B04001084_moe"
    }, 
    {
      "id": "us/census/acs/B04001085_moe"
    }, 
    {
      "id": "us/census/acs/B04001086_moe"
    }, 
    {
      "id": "us/census/acs/B04001087_moe"
    }, 
    {
      "id": "us/census/acs/B04001088_moe"
    }, 
    {
      "id": "us/census/acs/B04001089_moe"
    }, 
    {
      "id": "us/census/acs/B04001090_moe"
    }, 
    {
      "id": "us/census/acs/B04001091_moe"
    }, 
    {
      "id": "us/census/acs/B04001092_moe"
    }, 
    {
      "id": "us/census/acs/B04001093_moe"
    }, 
    {
      "id": "us/census/acs/B04001094_moe"
    }, 
    {
      "id": "us/census/acs/B04001095_moe"
    }, 
    {
      "id": "us/census/acs/B04001096_moe"
    }, 
    {
      "id": "us/census/acs/B04001097_moe"
    }, 
    {
      "id": "us/census/acs/B04001098_moe"
    }, 
    {
      "id": "us/census/acs/B04001099_moe"
    }, 
    {
      "id": "us/census/acs/B04001100_moe"
    }, 
    {
      "id": "us/census/acs/B04001101_moe"
    }, 
    {
      "id": "us/census/acs/B04001102_moe"
    }, 
    {
      "id": "us/census/acs/B04001103_moe"
    }, 
    {
      "id": "us/census/acs/B04001104_moe"
    }, 
    {
      "id": "us/census/acs/B04001105_moe"
    }, 
    {
      "id": "us/census/acs/B04001106_moe"
    }, 
    {
      "id": "us/census/acs/B04001107_moe"
    }, 
    {
      "id": "us/census/acs/B04001108_moe"
    }, 
    {
      "id": "us/census/acs/B04001109_moe"
    }, 
    {
      "id": "us/census/acs/C04001001_moe"
    }, 
    {
      "id": "us/census/acs/C04001002_moe"
    }, 
    {
      "id": "us/census/acs/C04001003_moe"
    }, 
    {
      "id": "us/census/acs/C04001004_moe"
    }, 
    {
      "id": "us/census/acs/C04001005_moe"
    }, 
    {
      "id": "us/census/acs/C04001006_moe"
    }, 
    {
      "id": "us/census/acs/C04001007_moe"
    }, 
    {
      "id": "us/census/acs/C04001008_moe"
    }, 
    {
      "id": "us/census/acs/C04001009_moe"
    }, 
    {
      "id": "us/census/acs/C04001010_moe"
    }, 
    {
      "id": "us/census/acs/C04001011_moe"
    }, 
    {
      "id": "us/census/acs/C04001012_moe"
    }, 
    {
      "id": "us/census/acs/C04001013_moe"
    }, 
    {
      "id": "us/census/acs/C04001014_moe"
    }, 
    {
      "id": "us/census/acs/C04001015_moe"
    }, 
    {
      "id": "us/census/acs/C04001016_moe"
    }, 
    {
      "id": "us/census/acs/C04001017_moe"
    }, 
    {
      "id": "us/census/acs/C04001018_moe"
    }, 
    {
      "id": "us/census/acs/C04001019_moe"
    }, 
    {
      "id": "us/census/acs/C04001020_moe"
    }, 
    {
      "id": "us/census/acs/C04001021_moe"
    }, 
    {
      "id": "us/census/acs/C04001022_moe"
    }, 
    {
      "id": "us/census/acs/C04001023_moe"
    }, 
    {
      "id": "us/census/acs/C04001024_moe"
    }, 
    {
      "id": "us/census/acs/C04001025_moe"
    }, 
    {
      "id": "us/census/acs/C04001026_moe"
    }, 
    {
      "id": "us/census/acs/C04001027_moe"
    }, 
    {
      "id": "us/census/acs/C04001028_moe"
    }, 
    {
      "id": "us/census/acs/C04001029_moe"
    }, 
    {
      "id": "us/census/acs/C04001030_moe"
    }, 
    {
      "id": "us/census/acs/C04001031_moe"
    }, 
    {
      "id": "us/census/acs/C04001032_moe"
    }
  ], 
  "dct_temporal_sm": 2013, 
  "title": "acs2013_1yr seq0007_moe"
}