{
  "extra": {
    "isDenominator": false, 
    "margin_of_error": true, 
    "table": "Receipt of Food Stamps/SNAP in the Past 12 Months by Presence of Children Under 18 Years by Household Type for Households", 
    "title": "Male householder, no wife present", 
    "universe": "Households"
  }, 
  "name": "Margin of error for Male householder, no wife present Household received Food Stamps/SNAP in the past 12 months Receipt of Food Stamps/SNAP in the Past 12 Months With children under 18 years Presence of Children Under 18 Years Other family Household Type", 
  "relationships": {
    "parent": "data/columns/us/census/acs/B22002/B22002006.json"
  }, 
  "tags": [
    "public assistance", 
    "families", 
    "children"
  ], 
  "weight": 0
}