{
  "aggregate": "sum", 
  "extra": {
    "ancestors": [
      "Hispanic or Latino:", 
      "South American:"
    ], 
    "table": "Hispanic or Latino Origin by Specific Origin", 
    "title": "Chilean", 
    "universe": "Total Population"
  }, 
  "name": "Chilean Specific Origin Hispanic or Latino Hispanic or Latino Origin South American Population", 
  "relationships": {
    "denominator": "us/census/acs/B03001001", 
    "parent": "us/census/acs/B03001016"
  }, 
  "tags": [
    "race"
  ], 
  "value": 0
}