{
  "aggregate": "sum", 
  "extra": {
    "ancestors": [
      "With a mortgage:"
    ], 
    "table": "Mortgage Status by Monthly Housing Costs as a Percentage of Household Income in the Past 12 Months", 
    "title": "Zero or negative income", 
    "universe": "Owner-occupied Housing Units"
  }, 
  "name": "Zero or negative income Monthly Housing Costs as a Percentage of Household Income in the Past 12 Months With a mortgage in Owner-occupied Housing Units", 
  "relationships": {
    "denominator": "us/census/acs/B25101001", 
    "parent": "us/census/acs/B25101002"
  }, 
  "tags": [
    "costs and value", 
    "housing", 
    "families", 
    "mortgage", 
    "income"
  ], 
  "value": 0
}