{
  "extra": {
    "margin_of_error": true, 
    "table": "Household Income in the Past 12 Months (In 2013 Inflation-adjusted Dollars) by Gross Rent", 
    "title": "No cash rent", 
    "universe": "Renter-occupied Housing Units"
  }, 
  "name": "Margin of error for No cash rent Gross Rent Renter occupied Household Income in the Past 12 Months (In 2013 Inflation-adjusted Dollars) $50,000 to $74,999 in Renter-occupied Housing Units", 
  "relationships": {
    "parent": "data/columns/us/census/acs/C25122026"
  }, 
  "tags": [
    "costs and value", 
    "housing", 
    "families", 
    "income"
  ], 
  "value": 0
}