{
  "extra": {
    "isDenominator": false, 
    "margin_of_error": true, 
    "table": "Imputation of Individuals' Income in the Past 12 Months for the Population 15 Years and Over - Percent of Income Imputed", 
    "title": "No income imputed", 
    "universe": "Population 15 Years and Over"
  }, 
  "name": "Margin of error for No income imputed in Population 15 Years and Over", 
  "relationships": {
    "parent": "data/columns/us/census/acs/B99191/B99191002.json"
  }, 
  "tags": [
    "technical", 
    "income"
  ], 
  "weight": 0
}